apb_pandas_utils/__init__.py
apb_pandas_utils/geopandas_utils.py
apb_pandas_utils/oracle_pandas.py
apb_pandas_utils-1.1.1.dist-info/METADATA
apb_pandas_utils-1.1.1.dist-info/WHEEL
apb_pandas_utils-1.1.1.dist-info/top_level.txt
apb_pandas_utils-1.1.1.dist-info/RECORD
